chastack/__init__.py
chastack-0.1.0.dist-info/LICENSE
chastack-0.1.0.dist-info/METADATA
chastack-0.1.0.dist-info/WHEEL
chastack-0.1.0.dist-info/top_level.txt
chastack-0.1.0.dist-info/RECORD
