Metadata-Version: 2.2
Name: chastack
Version: 0.1.0
Home-page: https://github.com/Hernanatn/chastack
Author: Hernán A. Teszkiewicz Novick
Author-email: "Hernán A.T.N." <herni@cajadeideas.ar>, "Joaquín C." <correajoaquin7@gmail.com>
Requires-Python: >=3.12
License-File: LICENSE
Requires-Dist: requests
Requires-Dist: zeep
Requires-Dist: xlsxwriter
Requires-Dist: pillow
Requires-Dist: flask
Requires-Dist: Flask-Caching
Requires-Dist: flask-cdn
Requires-Dist: flask-compress
Requires-Dist: flask-babel
Requires-Dist: Flask-Minify
Requires-Dist: google-api-python-client
Requires-Dist: google-auth-httplib2
Requires-Dist: google-auth-oauthlib
Requires-Dist: sobrecargar
Requires-Dist: solteron
Requires-Dist: chastack-bdd
Requires-Dist: chastack-utiles-flask
Requires-Dist: chastack-utiles-google
Dynamic: author
Dynamic: home-page
